cartesia_metal/__init__.py
cartesia_metal-0.0.0.dist-info/METADATA
cartesia_metal-0.0.0.dist-info/WHEEL
cartesia_metal-0.0.0.dist-info/top_level.txt
cartesia_metal-0.0.0.dist-info/RECORD
