Metadata-Version: 2.1
Name: cartesia-metal
Version: 0.0.0
Summary: Coming soon
Author-email: "Cartesia AI, Inc." <support@cartesia.ai>
